instaOS/__init__.py
instaOS/instagram.py
instaOS-0.0.3.dist-info/LICENSE
instaOS-0.0.3.dist-info/METADATA
instaOS-0.0.3.dist-info/WHEEL
instaOS-0.0.3.dist-info/top_level.txt
instaOS-0.0.3.dist-info/RECORD
