Metadata-Version: 2.1
Name: instaOS
Version: 0.0.3
Summary: Instagram followers list and following list
Home-page: UNKNOWN
Author: Umit KOC
Author-email: umitkoc.com@gmail.com
License: UNKNOWN
Keywords: instagram,followers,following,not following
Platform: UNKNOWN
Classifier: Development Status :: 1 - Planning
Classifier: Intended Audience :: Developers
Classifier: Programming Language :: Python :: 3
Classifier: Operating System :: Unix
Classifier: Operating System :: MacOS :: MacOS X
Classifier: Operating System :: Microsoft :: Windows
License-File: LICENSE
Requires-Dist: chromedriver-autoinstaller
Requires-Dist: python-dotenv
Requires-Dist: selenium
Requires-Dist: tqdm
Requires-Dist: webdriver-manager
